{
  "meta": {
    "schema_version": 1,
    "generated_at": "2026-06-23T23:20:00.205369+00:00",
    "session_phase": "afterhours"
  },
  "scanner": {
    "pi_candidates": [
      {
        "symbol": "CTRA",
        "price": 32.49,
        "prev_close": 35.63,
        "change_pct": -8.81,
        "today_volume": 73319896,
        "avg_daily_volume": 11311947,
        "volume_ratio": 8.42,
        "day_high": 34.06,
        "day_low": 32.46,
        "yesterday": {
          "open": 35.8,
          "high": 36.31,
          "low": 35.44,
          "close": 35.63,
          "volume": 8705790
        },
        "score": 25.56,
        "technicals": {
          "atr_14": 1.3046,
          "atr_pct": 4.02,
          "20d_high": 36.31,
          "pct_from_20d_high": -10.53,
          "20d_low": 29.34,
          "pct_from_20d_low": 10.75,
          "5d_change_pct": -8.74,
          "recent_bars": [
            {
              "date": "2026-04-30",
              "open": 35.0,
              "high": 36.0,
              "low": 34.75,
              "close": 35.91,
              "volume": 5860111
            },
            {
              "date": "2026-05-01",
              "open": 35.5,
              "high": 35.66,
              "low": 34.68,
              "close": 35.38,
              "volume": 6543376
            },
            {
              "date": "2026-05-04",
              "open": 35.57,
              "high": 36.15,
              "low": 35.23,
              "close": 35.86,
              "volume": 5584881
            },
            {
              "date": "2026-05-05",
              "open": 35.8,
              "high": 36.31,
              "low": 35.44,
              "close": 35.63,
              "volume": 8705789
            },
            {
              "date": "2026-05-06",
              "open": 33.45,
              "high": 34.06,
              "low": 32.46,
              "close": 32.56,
              "volume": 73319896
            }
          ]
        }
      },
      {
        "symbol": "IVZ",
        "price": 27.02,
        "prev_close": 28.78,
        "change_pct": -6.12,
        "today_volume": 10811046,
        "avg_daily_volume": 5456260,
        "volume_ratio": 2.96,
        "day_high": 28.49,
        "day_low": 26.68,
        "yesterday": {
          "open": 28.23,
          "high": 28.78,
          "low": 28.06,
          "close": 28.78,
          "volume": 3656766
        },
        "score": 10.53,
        "technicals": {
          "atr_14": 1.0043,
          "atr_pct": 3.72,
          "20d_high": 29.82,
          "pct_from_20d_high": -9.37,
          "20d_low": 26.68,
          "pct_from_20d_low": 1.26,
          "50d_ma": 26.95,
          "pct_from_50d_ma": 0.26,
          "above_50d_ma": true,
          "5d_change_pct": -7.15,
          "recent_bars": [
            {
              "date": "2026-06-16",
              "open": 29.43,
              "high": 29.59,
              "low": 29.09,
              "close": 29.2,
              "volume": 2901200
            },
            {
              "date": "2026-06-17",
              "open": 29.21,
              "high": 29.65,
              "low": 28.65,
              "close": 28.79,
              "volume": 5777439
            },
            {
              "date": "2026-06-18",
              "open": 29.16,
              "high": 29.3,
              "low": 27.81,
              "close": 28.14,
              "volume": 11867991
            },
            {
              "date": "2026-06-22",
              "open": 28.23,
              "high": 28.78,
              "low": 28.06,
              "close": 28.78,
              "volume": 3656766
            },
            {
              "date": "2026-06-23",
              "open": 28.21,
              "high": 28.49,
              "low": 26.68,
              "close": 27.02,
              "volume": 10811046
            }
          ]
        }
      },
      {
        "symbol": "MUR",
        "price": 36.02,
        "prev_close": 34.42,
        "change_pct": 4.65,
        "today_volume": 4065560,
        "avg_daily_volume": 3036563,
        "volume_ratio": 2.24,
        "day_high": 36.46,
        "day_low": 34.58,
        "yesterday": {
          "open": 34.57,
          "high": 34.9,
          "low": 34.09,
          "close": 34.42,
          "volume": 1815017
        },
        "score": 6.96,
        "technicals": {
          "atr_14": 1.5824,
          "atr_pct": 4.39,
          "20d_high": 40.67,
          "pct_from_20d_high": -11.44,
          "20d_low": 33.73,
          "pct_from_20d_low": 6.77,
          "50d_ma": 38.41,
          "pct_from_50d_ma": -6.23,
          "above_50d_ma": false,
          "5d_change_pct": -1.18,
          "recent_bars": [
            {
              "date": "2026-06-16",
              "open": 35.72,
              "high": 36.2,
              "low": 35.52,
              "close": 35.7,
              "volume": 1515617
            },
            {
              "date": "2026-06-17",
              "open": 35.53,
              "high": 36.05,
              "low": 34.97,
              "close": 35.27,
              "volume": 2023287
            },
            {
              "date": "2026-06-18",
              "open": 34.8,
              "high": 34.8,
              "low": 33.73,
              "close": 34.29,
              "volume": 2967336
            },
            {
              "date": "2026-06-22",
              "open": 34.57,
              "high": 34.9,
              "low": 34.09,
              "close": 34.42,
              "volume": 1815017
            },
            {
              "date": "2026-06-23",
              "open": 35.0,
              "high": 36.46,
              "low": 34.58,
              "close": 36.02,
              "volume": 4065560
            }
          ]
        }
      },
      {
        "symbol": "CG",
        "price": 42.85,
        "prev_close": 44.57,
        "change_pct": -3.86,
        "today_volume": 4568135,
        "avg_daily_volume": 3363432,
        "volume_ratio": 2.42,
        "day_high": 44.68,
        "day_low": 42.64,
        "yesterday": {
          "open": 44.76,
          "high": 45.27,
          "low": 43.98,
          "close": 44.57,
          "volume": 1887835
        },
        "score": 6.0,
        "technicals": {
          "atr_14": 1.6792,
          "atr_pct": 3.92,
          "20d_high": 47.63,
          "pct_from_20d_high": -10.04,
          "20d_low": 41.54,
          "pct_from_20d_low": 3.15,
          "50d_ma": 47.47,
          "pct_from_50d_ma": -9.74,
          "above_50d_ma": false,
          "5d_change_pct": -7.2,
          "recent_bars": [
            {
              "date": "2026-06-16",
              "open": 46.84,
              "high": 47.23,
              "low": 46.25,
              "close": 46.83,
              "volume": 2894058
            },
            {
              "date": "2026-06-17",
              "open": 46.23,
              "high": 47.55,
              "low": 45.56,
              "close": 45.69,
              "volume": 2097321
            },
            {
              "date": "2026-06-18",
              "open": 46.2,
              "high": 46.3,
              "low": 44.65,
              "close": 44.8,
              "volume": 3462808
            },
            {
              "date": "2026-06-22",
              "open": 44.76,
              "high": 45.27,
              "low": 43.98,
              "close": 44.57,
              "volume": 1887835
            },
            {
              "date": "2026-06-23",
              "open": 44.34,
              "high": 44.68,
              "low": 42.64,
              "close": 42.91,
              "volume": 4568135
            }
          ]
        }
      },
      {
        "symbol": "JEF",
        "price": 60.52,
        "prev_close": 62.81,
        "change_pct": -3.65,
        "today_volume": 5145991,
        "avg_daily_volume": 3649330,
        "volume_ratio": 2.34,
        "day_high": 62.0,
        "day_low": 60.33,
        "yesterday": {
          "open": 62.65,
          "high": 63.47,
          "low": 62.53,
          "close": 62.81,
          "volume": 2197767
        },
        "score": 5.58,
        "technicals": {
          "atr_14": 1.876,
          "atr_pct": 3.1,
          "20d_high": 63.98,
          "pct_from_20d_high": -5.41,
          "20d_low": 51.22,
          "pct_from_20d_low": 18.16,
          "50d_ma": 52.72,
          "pct_from_50d_ma": 14.79,
          "above_50d_ma": true,
          "5d_change_pct": -2.31,
          "recent_bars": [
            {
              "date": "2026-06-16",
              "open": 62.6,
              "high": 63.39,
              "low": 61.9,
              "close": 62.02,
              "volume": 1644849
            },
            {
              "date": "2026-06-17",
              "open": 62.37,
              "high": 63.98,
              "low": 61.82,
              "close": 61.88,
              "volume": 2269147
            },
            {
              "date": "2026-06-18",
              "open": 61.69,
              "high": 62.93,
              "low": 61.5,
              "close": 62.1,
              "volume": 3011386
            },
            {
              "date": "2026-06-22",
              "open": 62.65,
              "high": 63.47,
              "low": 62.53,
              "close": 62.81,
              "volume": 2197767
            },
            {
              "date": "2026-06-23",
              "open": 61.47,
              "high": 62.0,
              "low": 60.33,
              "close": 60.52,
              "volume": 5145991
            }
          ]
        }
      }
    ],
    "scanner_file": "scan_20260623_203000.json",
    "scanner_age_seconds": 10199,
    "market_context": {
      "SPY": {
        "price": 734.4,
        "change_pct": -1.34,
        "day_high": 739.63,
        "day_low": 732.3
      },
      "QQQ": {
        "price": 715.74,
        "change_pct": -3.01,
        "day_high": 723.61,
        "day_low": 712.11
      },
      "IWM": {
        "price": 295.52,
        "change_pct": -0.89,
        "day_high": 297.75,
        "day_low": 292.4
      },
      "DIA": {
        "price": 516.5,
        "change_pct": -0.11,
        "day_high": 518.72,
        "day_low": 512.97
      },
      "XLE": {
        "price": 54.41,
        "change_pct": 0.66,
        "day_high": 54.56,
        "day_low": 53.87
      },
      "XLK": {
        "price": 184.93,
        "change_pct": -3.76,
        "day_high": 187.25,
        "day_low": 183.7
      },
      "XLF": {
        "price": 53.83,
        "change_pct": 0.25,
        "day_high": 54.02,
        "day_low": 53.49
      },
      "XLV": {
        "price": 152.13,
        "change_pct": 1.38,
        "day_high": 152.43,
        "day_low": 151.0
      },
      "XLI": {
        "price": 178.2,
        "change_pct": -1.98,
        "day_high": 180.01,
        "day_low": 177.23
      },
      "XLY": {
        "price": 114.06,
        "change_pct": -0.77,
        "day_high": 114.66,
        "day_low": 113.47
      },
      "XLP": {
        "price": 83.75,
        "change_pct": 1.91,
        "day_high": 83.84,
        "day_low": 83.03
      },
      "XLU": {
        "price": 45.08,
        "change_pct": 0.81,
        "day_high": 45.2,
        "day_low": 44.46
      },
      "XLB": {
        "price": 50.81,
        "change_pct": -1.57,
        "day_high": 51.48,
        "day_low": 50.79
      },
      "XLRE": {
        "price": 44.64,
        "change_pct": 1.41,
        "day_high": 44.72,
        "day_low": 44.09
      },
      "SMH": {
        "price": 625.0,
        "change_pct": -6.56,
        "day_high": 636.88,
        "day_low": 617.27
      }
    },
    "filters": {
      "min_change_pct": 1.5,
      "min_volume_ratio": 2.0,
      "max_candidates": 30
    },
    "universe_size": 446
  },
  "calendar": {
    "earnings_yesterday_ah": [
      {
        "symbol": "BSFC",
        "date": "2026-06-22",
        "hour": "amc",
        "eps_estimate": null,
        "eps_actual": null,
        "rev_estimate": null,
        "rev_actual": null,
        "year": 2025,
        "quarter": 4
      }
    ],
    "earnings_today_bmo": [
      {
        "symbol": "JFIN",
        "date": "2026-06-23",
        "hour": "bmo",
        "eps_estimate": null,
        "eps_actual": -1.085312,
        "rev_estimate": null,
        "rev_actual": 744117040,
        "year": 2026,
        "quarter": 1
      },
      {
        "symbol": "KFY",
        "date": "2026-06-23",
        "hour": "bmo",
        "eps_estimate": 1.3938,
        "eps_actual": 1.4,
        "rev_estimate": 750773198,
        "rev_actual": 759770000,
        "year": 2026,
        "quarter": 4
      },
      {
        "symbol": "SUNB",
        "date": "2026-06-23",
        "hour": "bmo",
        "eps_estimate": 0.771,
        "eps_actual": 0.74,
        "rev_estimate": 2694113352,
        "rev_actual": 2754000000,
        "year": 2026,
        "quarter": 4
      }
    ],
    "earnings_today_ah": [
      {
        "symbol": "CBRS",
        "date": "2026-06-23",
        "hour": "amc",
        "eps_estimate": -0.1644,
        "eps_actual": -0.04,
        "rev_estimate": 185221361,
        "rev_actual": 193410000,
        "year": 2026,
        "quarter": 1
      },
      {
        "symbol": "FDX",
        "date": "2026-06-23",
        "hour": "amc",
        "eps_estimate": 6.0169,
        "eps_actual": 6.31,
        "rev_estimate": 24276403682,
        "rev_actual": 25007000000,
        "year": 2026,
        "quarter": 4
      },
      {
        "symbol": "GIS",
        "date": "2026-06-23",
        "hour": "amc",
        "eps_estimate": 0.8084,
        "eps_actual": null,
        "rev_estimate": 4640475168,
        "rev_actual": null,
        "year": 2026,
        "quarter": 4
      },
      {
        "symbol": "KBH",
        "date": "2026-06-23",
        "hour": "amc",
        "eps_estimate": 0.4504,
        "eps_actual": 0.43,
        "rev_estimate": 1107932630,
        "rev_actual": 1112440000,
        "year": 2026,
        "quarter": 2
      },
      {
        "symbol": "KEQU",
        "date": "2026-06-23",
        "hour": "amc",
        "eps_estimate": null,
        "eps_actual": 1.14,
        "rev_estimate": null,
        "rev_actual": 71400000,
        "year": 2026,
        "quarter": 4
      },
      {
        "symbol": "WOR",
        "date": "2026-06-23",
        "hour": "amc",
        "eps_estimate": 1.0706,
        "eps_actual": 0.97,
        "rev_estimate": 390357930,
        "rev_actual": 371460000,
        "year": 2026,
        "quarter": 4
      }
    ],
    "econ_data_today": null,
    "fetch_status": {
      "earnings": "ok",
      "economic": "failed: forbidden: {\"error\":\"You don't have access to this resource.\"}"
    }
  },
  "macro": {
    "fetch_status": "ok",
    "futures_proxy": [
      {
        "symbol": "SPY",
        "label": "S&P 500",
        "proxy_for": "ES futures / SPX",
        "last": 733.85,
        "prev_close": 744.39,
        "change_pct": -1.42,
        "day_high": 739.63,
        "day_low": 732.3,
        "volume": 67170843
      },
      {
        "symbol": "QQQ",
        "label": "Nasdaq 100",
        "proxy_for": "NQ futures / NDX",
        "last": 714.17,
        "prev_close": 737.95,
        "change_pct": -3.22,
        "day_high": 723.61,
        "day_low": 712.11,
        "volume": 53410709
      },
      {
        "symbol": "DIA",
        "label": "Dow Jones",
        "proxy_for": "YM futures / DJIA",
        "last": 516.32,
        "prev_close": 517.08,
        "change_pct": -0.15,
        "day_high": 518.72,
        "day_low": 512.97,
        "volume": 5039817
      },
      {
        "symbol": "IWM",
        "label": "Russell 2000",
        "proxy_for": "RTY futures / RUT",
        "last": 295.05,
        "prev_close": 298.18,
        "change_pct": -1.05,
        "day_high": 297.75,
        "day_low": 292.4,
        "volume": 26804128
      }
    ],
    "commodities": [
      {
        "symbol": "USO",
        "label": "Oil (WTI proxy)",
        "proxy_for": "WTI crude",
        "last": 110.61,
        "prev_close": 112.69,
        "change_pct": -1.85,
        "day_high": 111.53,
        "day_low": 110.06,
        "volume": 3125992
      },
      {
        "symbol": "UNG",
        "label": "Natural gas",
        "proxy_for": "NG futures",
        "last": 11.5,
        "prev_close": 11.77,
        "change_pct": -2.29,
        "day_high": 11.66,
        "day_low": 11.41,
        "volume": 5614575
      },
      {
        "symbol": "GLD",
        "label": "Gold",
        "proxy_for": "Gold futures",
        "last": 376.21,
        "prev_close": 384.59,
        "change_pct": -2.18,
        "day_high": 380.35,
        "day_low": 377.17,
        "volume": 7518561
      }
    ],
    "vol_and_dollar": [
      {
        "symbol": "VIXY",
        "label": "VIX (proxy)",
        "proxy_for": "^VIX (imperfect \u2014 VIX ETF has decay)",
        "last": 23.01,
        "prev_close": 21.85,
        "change_pct": 5.31,
        "day_high": 23.26,
        "day_low": 22.54,
        "volume": 3339329
      },
      {
        "symbol": "UUP",
        "label": "US Dollar",
        "proxy_for": "DXY",
        "last": 28.45,
        "prev_close": 28.36,
        "change_pct": 0.32,
        "day_high": 28.48,
        "day_low": 28.4,
        "volume": 2494783
      },
      {
        "symbol": "TLT",
        "label": "20Y Treasuries",
        "proxy_for": "Long bonds \u2014 inverse to long yields",
        "last": 86.14,
        "prev_close": 86.09,
        "change_pct": 0.06,
        "day_high": 86.42,
        "day_low": 86.1,
        "volume": 19153132
      }
    ],
    "asia": [
      {
        "symbol": "EWJ",
        "label": "Japan",
        "proxy_for": "Nikkei / TOPIX",
        "last": 92.81,
        "prev_close": 96.97,
        "change_pct": -4.29,
        "day_high": 93.34,
        "day_low": 92.09,
        "volume": 11167346
      },
      {
        "symbol": "FXI",
        "label": "China large-cap",
        "proxy_for": "HSI / CSI300",
        "last": 32.83,
        "prev_close": 33.43,
        "change_pct": -1.79,
        "day_high": 33.01,
        "day_low": 32.76,
        "volume": 24400016
      },
      {
        "symbol": "EWY",
        "label": "South Korea",
        "proxy_for": "KOSPI",
        "last": 195.26,
        "prev_close": 219.02,
        "change_pct": -10.85,
        "day_high": 201.05,
        "day_low": 191.33,
        "volume": 43498100
      },
      {
        "symbol": "EWT",
        "label": "Taiwan",
        "proxy_for": "TAIEX",
        "last": 105.6,
        "prev_close": 111.53,
        "change_pct": -5.32,
        "day_high": 106.74,
        "day_low": 105.0,
        "volume": 8882863
      }
    ],
    "europe": [
      {
        "symbol": "EWG",
        "label": "Germany",
        "proxy_for": "DAX",
        "last": 40.98,
        "prev_close": 41.54,
        "change_pct": -1.35,
        "day_high": 41.17,
        "day_low": 40.95,
        "volume": 1123458
      },
      {
        "symbol": "EWU",
        "label": "UK",
        "proxy_for": "FTSE 100",
        "last": 45.57,
        "prev_close": 45.69,
        "change_pct": -0.26,
        "day_high": 45.71,
        "day_low": 45.5,
        "volume": 767712
      },
      {
        "symbol": "EWQ",
        "label": "France",
        "proxy_for": "CAC 40",
        "last": 44.75,
        "prev_close": 45.21,
        "change_pct": -1.02,
        "day_high": 44.97,
        "day_low": 44.74,
        "volume": 235409
      },
      {
        "symbol": "VGK",
        "label": "Europe broad",
        "proxy_for": "STOXX 600 broad",
        "last": 87.17,
        "prev_close": 88.25,
        "change_pct": -1.22,
        "day_high": 87.56,
        "day_low": 87.02,
        "volume": 3015934
      }
    ],
    "sectors_extra": [
      {
        "symbol": "XLE",
        "label": "Energy",
        "proxy_for": "Sector",
        "last": 54.5,
        "prev_close": 54.06,
        "change_pct": 0.81,
        "day_high": 54.56,
        "day_low": 53.87,
        "volume": 38690751
      },
      {
        "symbol": "XLF",
        "label": "Financials",
        "proxy_for": "Sector",
        "last": 53.85,
        "prev_close": 53.7,
        "change_pct": 0.28,
        "day_high": 54.02,
        "day_low": 53.49,
        "volume": 33375666
      },
      {
        "symbol": "XLI",
        "label": "Industrials",
        "proxy_for": "Sector",
        "last": 178.01,
        "prev_close": 181.8,
        "change_pct": -2.08,
        "day_high": 180.01,
        "day_low": 177.23,
        "volume": 8928704
      },
      {
        "symbol": "SMH",
        "label": "Semis",
        "proxy_for": "PHLX SOX proxy",
        "last": 623.13,
        "prev_close": 668.91,
        "change_pct": -6.84,
        "day_high": 636.88,
        "day_low": 617.27,
        "volume": 19142228
      },
      {
        "symbol": "XLK",
        "label": "Technology",
        "proxy_for": "Sector",
        "last": 184.35,
        "prev_close": 192.15,
        "change_pct": -4.06,
        "day_high": 187.25,
        "day_low": 183.7,
        "volume": 14634000
      }
    ]
  },
  "halts": {
    "fetch_status": "ok",
    "halts_today": [
      {
        "ticker": "SRXH",
        "halt_reason": "",
        "title": "SRXH",
        "description": "Halt DateHalt TimeIssue SymbolIssue NameMarketReason CodePause Threshold PriceResumption DateResumption Quote TimeResumption Trade Time06/23/2026                    16:13:37.528SRXHSRX Health Solutions, Inc.AMEXT1",
        "published": "Tue, 23 Jun 2026 04:00:00 GMT"
      },
      {
        "ticker": "JXG",
        "halt_reason": "",
        "title": "JXG",
        "description": "Halt DateHalt TimeIssue SymbolIssue NameMarketReason CodePause Threshold PriceResumption DateResumption Quote TimeResumption Trade Time06/23/2026                    15:58:56.440JXGJX Luxventure Group Inc CmnNASDAQLUDP06/23/2026                    15:58:56                      16:00:00",
        "published": "Tue, 23 Jun 2026 04:00:00 GMT"
      },
      {
        "ticker": "CLRO",
        "halt_reason": "",
        "title": "CLRO",
        "description": "Halt DateHalt TimeIssue SymbolIssue NameMarketReason CodePause Threshold PriceResumption DateResumption Quote TimeResumption Trade Time06/23/2026                    14:56:28.803CLROCLEARONE INC. Cmn StkNASDAQLUDP06/23/2026                    14:56:28                      15:01:28",
        "published": "Tue, 23 Jun 2026 04:00:00 GMT"
      },
      {
        "ticker": "ATLN",
        "halt_reason": "",
        "title": "ATLN",
        "description": "Halt DateHalt TimeIssue SymbolIssue NameMarketReason CodePause Threshold PriceResumption DateResumption Quote TimeResumption Trade Time06/23/2026                    14:31:10.933ATLNAtlantic International Corp CSNASDAQLUDP06/23/2026                    14:31:10                      14:36:10",
        "published": "Tue, 23 Jun 2026 04:00:00 GMT"
      },
      {
        "ticker": "ATLN",
        "halt_reason": "",
        "title": "ATLN",
        "description": "Halt DateHalt TimeIssue SymbolIssue NameMarketReason CodePause Threshold PriceResumption DateResumption Quote TimeResumption Trade Time06/23/2026                    14:21:54.133ATLNAtlantic International Corp CSNASDAQLUDP06/23/2026                    14:21:54                      14:26:54",
        "published": "Tue, 23 Jun 2026 04:00:00 GMT"
      },
      {
        "ticker": "ATLN",
        "halt_reason": "",
        "title": "ATLN",
        "description": "Halt DateHalt TimeIssue SymbolIssue NameMarketReason CodePause Threshold PriceResumption DateResumption Quote TimeResumption Trade Time06/23/2026                    14:07:27.986ATLNAtlantic International Corp CSNASDAQLUDP06/23/2026                    14:07:27                      14:12:27",
        "published": "Tue, 23 Jun 2026 04:00:00 GMT"
      },
      {
        "ticker": "STFS",
        "halt_reason": "",
        "title": "STFS",
        "description": "Halt DateHalt TimeIssue SymbolIssue NameMarketReason CodePause Threshold PriceResumption DateResumption Quote TimeResumption Trade Time06/23/2026                    13:39:01.093STFSStar Fash Clt Hldgs Ord ANASDAQLUDP06/23/2026                    13:39:01                      13:44:01",
        "published": "Tue, 23 Jun 2026 04:00:00 GMT"
      },
      {
        "ticker": "STFS",
        "halt_reason": "",
        "title": "STFS",
        "description": "Halt DateHalt TimeIssue SymbolIssue NameMarketReason CodePause Threshold PriceResumption DateResumption Quote TimeResumption Trade Time06/23/2026                    13:28:16.890STFSStar Fash Clt Hldgs Ord ANASDAQLUDP06/23/2026                    13:28:16                      13:38:26",
        "published": "Tue, 23 Jun 2026 04:00:00 GMT"
      },
      {
        "ticker": "CLRO",
        "halt_reason": "",
        "title": "CLRO",
        "description": "Halt DateHalt TimeIssue SymbolIssue NameMarketReason CodePause Threshold PriceResumption DateResumption Quote TimeResumption Trade Time06/23/2026                    13:06:44.276CLROCLEARONE INC. Cmn StkNASDAQLUDP06/23/2026                    13:06:44                      13:11:44",
        "published": "Tue, 23 Jun 2026 04:00:00 GMT"
      },
      {
        "ticker": "AUC",
        "halt_reason": "",
        "title": "AUC",
        "description": "Halt DateHalt TimeIssue SymbolIssue NameMarketReason CodePause Threshold PriceResumption DateResumption Quote TimeResumption Trade Time06/23/2026                    12:38:34.113AUCATIF Holdings Ltd Ord ShsNASDAQLUDP06/23/2026                    12:38:34                      12:43:34",
        "published": "Tue, 23 Jun 2026 04:00:00 GMT"
      },
      {
        "ticker": "BSAAU",
        "halt_reason": "",
        "title": "BSAAU",
        "description": "Halt DateHalt TimeIssue SymbolIssue NameMarketReason CodePause Threshold PriceResumption DateResumption Quote TimeResumption Trade Time06/23/2026                    11:46:44.123BSAAUBEST SPAC I Acquisition Corp UNASDAQLUDP06/23/2026                    11:46:44                      11:51:44",
        "published": "Tue, 23 Jun 2026 04:00:00 GMT"
      },
      {
        "ticker": "ATLN",
        "halt_reason": "",
        "title": "ATLN",
        "description": "Halt DateHalt TimeIssue SymbolIssue NameMarketReason CodePause Threshold PriceResumption DateResumption Quote TimeResumption Trade Time06/23/2026                    11:26:30.503ATLNAtlantic International Corp CSNASDAQLUDP06/23/2026                    11:26:30                      11:31:30",
        "published": "Tue, 23 Jun 2026 04:00:00 GMT"
      },
      {
        "ticker": "FCUV",
        "halt_reason": "",
        "title": "FCUV",
        "description": "Halt DateHalt TimeIssue SymbolIssue NameMarketReason CodePause Threshold PriceResumption DateResumption Quote TimeResumption Trade Time06/23/2026                    11:13:38.206FCUVFocus Universal Inc. CmNASDAQLUDP06/23/2026                    11:13:38                      11:18:38",
        "published": "Tue, 23 Jun 2026 04:00:00 GMT"
      },
      {
        "ticker": "FCUV",
        "halt_reason": "",
        "title": "FCUV",
        "description": "Halt DateHalt TimeIssue SymbolIssue NameMarketReason CodePause Threshold PriceResumption DateResumption Quote TimeResumption Trade Time06/23/2026                    11:00:25.273FCUVFocus Universal Inc. CmNASDAQLUDP06/23/2026                    11:00:25                      11:10:25",
        "published": "Tue, 23 Jun 2026 04:00:00 GMT"
      },
      {
        "ticker": "MARB",
        "halt_reason": "",
        "title": "MARB",
        "description": "Halt DateHalt TimeIssue SymbolIssue NameMarketReason CodePause Threshold PriceResumption DateResumption Quote TimeResumption Trade Time06/23/2026                    10:58:49.940MARBFirst Trust Merger Arbitrage ETFNYSE ArcaM06/23/2026                    11:03:49                      11:03:49",
        "published": "Tue, 23 Jun 2026 04:00:00 GMT"
      },
      {
        "ticker": "BLCN",
        "halt_reason": "",
        "title": "BLCN",
        "description": "Halt DateHalt TimeIssue SymbolIssue NameMarketReason CodePause Threshold PriceResumption DateResumption Quote TimeResumption Trade Time06/23/2026                    10:33:50.163BLCNSiren NexGen Economy ETFNASDAQLUDP06/23/2026                    10:33:50                      10:38:50",
        "published": "Tue, 23 Jun 2026 04:00:00 GMT"
      },
      {
        "ticker": "FGMCU",
        "halt_reason": "",
        "title": "FGMCU",
        "description": "Halt DateHalt TimeIssue SymbolIssue NameMarketReason CodePause Threshold PriceResumption DateResumption Quote TimeResumption Trade Time06/23/2026                    10:30:22.476FGMCUFG Merger II Corp. UnitNASDAQLUDP06/23/2026                    10:30:22                      10:35:22",
        "published": "Tue, 23 Jun 2026 04:00:00 GMT"
      },
      {
        "ticker": "TMS",
        "halt_reason": "",
        "title": "TMS",
        "description": "Halt DateHalt TimeIssue SymbolIssue NameMarketReason CodePause Threshold PriceResumption DateResumption Quote TimeResumption Trade Time06/23/2026                    10:27:39.953TMSTeamshares Inc. Common StockNASDAQLUDP06/23/2026                    10:27:39                      10:32:39",
        "published": "Tue, 23 Jun 2026 04:00:00 GMT"
      },
      {
        "ticker": "ONEG",
        "halt_reason": "",
        "title": "ONEG",
        "description": "Halt DateHalt TimeIssue SymbolIssue NameMarketReason CodePause Threshold PriceResumption DateResumption Quote TimeResumption Trade Time06/23/2026                    10:18:33.270ONEGOneConstruction Group Ltd ShsNASDAQLUDP06/23/2026                    10:18:33                      10:28:33",
        "published": "Tue, 23 Jun 2026 04:00:00 GMT"
      },
      {
        "ticker": "SDOT",
        "halt_reason": "",
        "title": "SDOT",
        "description": "Halt DateHalt TimeIssue SymbolIssue NameMarketReason CodePause Threshold PriceResumption DateResumption Quote TimeResumption Trade Time06/23/2026                    09:54:33.160SDOTSadot Group Inc CSNASDAQLUDP06/23/2026                    09:54:33                      09:59:33",
        "published": "Tue, 23 Jun 2026 04:00:00 GMT"
      },
      {
        "ticker": "ATLN",
        "halt_reason": "",
        "title": "ATLN",
        "description": "Halt DateHalt TimeIssue SymbolIssue NameMarketReason CodePause Threshold PriceResumption DateResumption Quote TimeResumption Trade Time06/23/2026                    09:52:58.353ATLNAtlantic International Corp CSNASDAQLUDP06/23/2026                    09:52:58                      09:57:58",
        "published": "Tue, 23 Jun 2026 04:00:00 GMT"
      },
      {
        "ticker": "FCUV",
        "halt_reason": "",
        "title": "FCUV",
        "description": "Halt DateHalt TimeIssue SymbolIssue NameMarketReason CodePause Threshold PriceResumption DateResumption Quote TimeResumption Trade Time06/23/2026                    09:52:11.056FCUVFocus Universal Inc. CmNASDAQLUDP06/23/2026                    09:52:11                      10:02:11",
        "published": "Tue, 23 Jun 2026 04:00:00 GMT"
      },
      {
        "ticker": "WYHG",
        "halt_reason": "",
        "title": "WYHG",
        "description": "Halt DateHalt TimeIssue SymbolIssue NameMarketReason CodePause Threshold PriceResumption DateResumption Quote TimeResumption Trade Time06/23/2026                    09:49:49.520WYHGWing Yip Fd Hldgs Grp ADSNASDAQLUDP06/23/2026                    09:49:49                      09:54:49",
        "published": "Tue, 23 Jun 2026 04:00:00 GMT"
      },
      {
        "ticker": "RDGT",
        "halt_reason": "",
        "title": "RDGT",
        "description": "Halt DateHalt TimeIssue SymbolIssue NameMarketReason CodePause Threshold PriceResumption DateResumption Quote TimeResumption Trade Time06/23/2026                    09:45:12.523RDGTRidgetech, Inc. Ordinary ShareNASDAQLUDP06/23/2026                    09:45:12                      09:50:12",
        "published": "Tue, 23 Jun 2026 04:00:00 GMT"
      },
      {
        "ticker": "SDOT",
        "halt_reason": "",
        "title": "SDOT",
        "description": "Halt DateHalt TimeIssue SymbolIssue NameMarketReason CodePause Threshold PriceResumption DateResumption Quote TimeResumption Trade Time06/23/2026                    09:42:52.463SDOTSadot Group Inc CSNASDAQLUDP06/23/2026                    09:42:52                      09:52:53",
        "published": "Tue, 23 Jun 2026 04:00:00 GMT"
      },
      {
        "ticker": "BSAA",
        "halt_reason": "",
        "title": "BSAA",
        "description": "Halt DateHalt TimeIssue SymbolIssue NameMarketReason CodePause Threshold PriceResumption DateResumption Quote TimeResumption Trade Time06/23/2026                    09:41:24.633BSAABEST SPAC I Acq Corp. Cl A OSNASDAQLUDP06/23/2026                    09:41:24                      09:46:24",
        "published": "Tue, 23 Jun 2026 04:00:00 GMT"
      },
      {
        "ticker": "WYHG",
        "halt_reason": "",
        "title": "WYHG",
        "description": "Halt DateHalt TimeIssue SymbolIssue NameMarketReason CodePause Threshold PriceResumption DateResumption Quote TimeResumption Trade Time06/23/2026                    09:37:48.213WYHGWing Yip Fd Hldgs Grp ADSNASDAQLUDP06/23/2026                    09:37:48                      09:47:48",
        "published": "Tue, 23 Jun 2026 04:00:00 GMT"
      },
      {
        "ticker": "MGRT",
        "halt_reason": "",
        "title": "MGRT",
        "description": "Halt DateHalt TimeIssue SymbolIssue NameMarketReason CodePause Threshold PriceResumption DateResumption Quote TimeResumption Trade Time06/23/2026                    09:35:45.843MGRTMega Fortune Co Ltd OrdNASDAQLUDP06/23/2026                    09:35:45                      09:40:45",
        "published": "Tue, 23 Jun 2026 04:00:00 GMT"
      },
      {
        "ticker": "ATLN",
        "halt_reason": "",
        "title": "ATLN",
        "description": "Halt DateHalt TimeIssue SymbolIssue NameMarketReason CodePause Threshold PriceResumption DateResumption Quote TimeResumption Trade Time06/23/2026                    09:32:13.680ATLNAtlantic International Corp CSNASDAQLUDP06/23/2026                    09:32:13                      09:37:13",
        "published": "Tue, 23 Jun 2026 04:00:00 GMT"
      },
      {
        "ticker": "GASZ",
        "halt_reason": "",
        "title": "GASZ",
        "description": "Halt DateHalt TimeIssue SymbolIssue NameMarketReason CodePause Threshold PriceResumption DateResumption Quote TimeResumption Trade Time06/23/2026                    09:31:43.433GASZCorgi Natural Gas Power & Turbines ETFNon NASDAQM06/23/2026                    09:36:43                      09:36:43",
        "published": "Tue, 23 Jun 2026 04:00:00 GMT"
      },
      {
        "ticker": "WYHG",
        "halt_reason": "",
        "title": "WYHG",
        "description": "Halt DateHalt TimeIssue SymbolIssue NameMarketReason CodePause Threshold PriceResumption DateResumption Quote TimeResumption Trade Time06/23/2026                    09:31:18.073WYHGWing Yip Fd Hldgs Grp ADSNASDAQLUDP06/23/2026                    09:31:18                      09:36:18",
        "published": "Tue, 23 Jun 2026 04:00:00 GMT"
      },
      {
        "ticker": "QTAC",
        "halt_reason": "",
        "title": "QTAC",
        "description": "Halt DateHalt TimeIssue SymbolIssue NameMarketReason CodePause Threshold PriceResumption DateResumption Quote TimeResumption Trade Time06/23/2026                    09:31:15.533QTACQ3 All-Season Tactical Advantage ETFNon NASDAQM06/23/2026                    09:36:15                      09:36:15",
        "published": "Tue, 23 Jun 2026 04:00:00 GMT"
      },
      {
        "ticker": "EZET",
        "halt_reason": "",
        "title": "EZET",
        "description": "Halt DateHalt TimeIssue SymbolIssue NameMarketReason CodePause Threshold PriceResumption DateResumption Quote TimeResumption Trade Time06/23/2026                    09:31:15.613EZETFranklin Ethereum ETFNon NASDAQM06/23/2026                    09:36:15                      09:36:15",
        "published": "Tue, 23 Jun 2026 04:00:00 GMT"
      },
      {
        "ticker": "QETH",
        "halt_reason": "",
        "title": "QETH",
        "description": "Halt DateHalt TimeIssue SymbolIssue NameMarketReason CodePause Threshold PriceResumption DateResumption Quote TimeResumption Trade Time06/23/2026                    09:31:07.926QETHInvesco Galaxy Ethereum ETFNon NASDAQM06/23/2026                    09:36:07                      09:36:07",
        "published": "Tue, 23 Jun 2026 04:00:00 GMT"
      },
      {
        "ticker": "TTXD",
        "halt_reason": "",
        "title": "TTXD",
        "description": "Halt DateHalt TimeIssue SymbolIssue NameMarketReason CodePause Threshold PriceResumption DateResumption Quote TimeResumption Trade Time06/23/2026                    09:30:21.520TTXDDirexion Daily Technology Top 5 Bear 2X ETFNYSE ArcaM06/23/2026                    09:35:21                      09:35:21",
        "published": "Tue, 23 Jun 2026 04:00:00 GMT"
      },
      {
        "ticker": "BOLD",
        "halt_reason": "",
        "title": "BOLD",
        "description": "Halt DateHalt TimeIssue SymbolIssue NameMarketReason CodePause Threshold PriceResumption DateResumption Quote TimeResumption Trade Time06/23/2026                    07:25:00.000BOLDBoundless Bio, Inc.NASDAQT306/23/2026                    07:45:00                      07:50:00",
        "published": "Tue, 23 Jun 2026 04:00:00 GMT"
      },
      {
        "ticker": "ILLR",
        "halt_reason": "",
        "title": "ILLR",
        "description": "Halt DateHalt TimeIssue SymbolIssue NameMarketReason CodePause Threshold PriceResumption DateResumption Quote TimeResumption Trade Time06/22/2026                    19:50:00.000ILLRTriller Group Inc Common StockNASDAQT306/23/2026                    08:55:00                      09:00:00",
        "published": "Mon, 22 Jun 2026 04:00:00 GMT"
      },
      {
        "ticker": "ILLRW",
        "halt_reason": "",
        "title": "ILLRW",
        "description": "Halt DateHalt TimeIssue SymbolIssue NameMarketReason CodePause Threshold PriceResumption DateResumption Quote TimeResumption Trade Time06/22/2026                    19:50:00.000ILLRWTriller Group Inc. WarrantNASDAQT306/23/2026                    09:00:00                      09:05:00",
        "published": "Mon, 22 Jun 2026 04:00:00 GMT"
      },
      {
        "ticker": "FCUV",
        "halt_reason": "",
        "title": "FCUV",
        "description": "Halt DateHalt TimeIssue SymbolIssue NameMarketReason CodePause Threshold PriceResumption DateResumption Quote TimeResumption Trade Time06/22/2026                    19:50:00.000FCUVFocus Universal Inc. CmNASDAQT306/23/2026                    08:55:00                      09:00:00",
        "published": "Mon, 22 Jun 2026 04:00:00 GMT"
      },
      {
        "ticker": "YYGH",
        "halt_reason": "",
        "title": "YYGH",
        "description": "Halt DateHalt TimeIssue SymbolIssue NameMarketReason CodePause Threshold PriceResumption DateResumption Quote TimeResumption Trade Time06/22/2026                    19:50:00.000YYGHYY Group Holding LimitedNASDAQT306/23/2026                    08:55:00                      09:00:00",
        "published": "Mon, 22 Jun 2026 04:00:00 GMT"
      },
      {
        "ticker": "HCHL",
        "halt_reason": "",
        "title": "HCHL",
        "description": "Halt DateHalt TimeIssue SymbolIssue NameMarketReason CodePause Threshold PriceResumption DateResumption Quote TimeResumption Trade Time06/11/2026                    19:50:00.000HCHLHappy City Holdings LimitedNASDAQH10",
        "published": "Thu, 11 Jun 2026 04:00:00 GMT"
      },
      {
        "ticker": "INHD",
        "halt_reason": "",
        "title": "INHD",
        "description": "Halt DateHalt TimeIssue SymbolIssue NameMarketReason CodePause Threshold PriceResumption DateResumption Quote TimeResumption Trade Time06/08/2026                    17:18:58.540INHDInno Holdings Inc.NASDAQT12",
        "published": "Mon, 08 Jun 2026 04:00:00 GMT"
      },
      {
        "ticker": "JDZG",
        "halt_reason": "",
        "title": "JDZG",
        "description": "Halt DateHalt TimeIssue SymbolIssue NameMarketReason CodePause Threshold PriceResumption DateResumption Quote TimeResumption Trade Time06/04/2026                    17:15:41.963JDZGJIADE LIMITED CL A OSNASDAQT12",
        "published": "Thu, 04 Jun 2026 04:00:00 GMT"
      },
      {
        "ticker": "SRL",
        "halt_reason": "",
        "title": "SRL",
        "description": "Halt DateHalt TimeIssue SymbolIssue NameMarketReason CodePause Threshold PriceResumption DateResumption Quote TimeResumption Trade Time05/12/2026                    10:29:37.918SRLScully Royalty Ltd.NYSEH11",
        "published": "Tue, 12 May 2026 04:00:00 GMT"
      },
      {
        "ticker": "MAGH",
        "halt_reason": "",
        "title": "MAGH",
        "description": "Halt DateHalt TimeIssue SymbolIssue NameMarketReason CodePause Threshold PriceResumption DateResumption Quote TimeResumption Trade Time12/04/2025                    19:50:00MAGHMagnitude International Ltd OSNASDAQT12",
        "published": "Thu, 04 Dec 2025 05:00:00 GMT"
      },
      {
        "ticker": "MAMK",
        "halt_reason": "",
        "title": "MAMK",
        "description": "Halt DateHalt TimeIssue SymbolIssue NameMarketReason CodePause Threshold PriceResumption DateResumption Quote TimeResumption Trade Time11/14/2025                    19:50:00MAMKMaxsMaking Inc.NASDAQT12",
        "published": "Fri, 14 Nov 2025 05:00:00 GMT"
      },
      {
        "ticker": "MCTA",
        "halt_reason": "",
        "title": "MCTA",
        "description": "Halt DateHalt TimeIssue SymbolIssue NameMarketReason CodePause Threshold PriceResumption DateResumption Quote TimeResumption Trade Time11/11/2025                    19:50:00MCTACharming Medical Limit Cl A OSNASDAQT12",
        "published": "Tue, 11 Nov 2025 05:00:00 GMT"
      },
      {
        "ticker": "LAWR",
        "halt_reason": "",
        "title": "LAWR",
        "description": "Halt DateHalt TimeIssue SymbolIssue NameMarketReason CodePause Threshold PriceResumption DateResumption Quote TimeResumption Trade Time10/22/2025                    19:50:00LAWRRobot Consulting ADSNASDAQT12",
        "published": "Wed, 22 Oct 2025 04:00:00 GMT"
      },
      {
        "ticker": "PC",
        "halt_reason": "",
        "title": "PC",
        "description": "Halt DateHalt TimeIssue SymbolIssue NameMarketReason CodePause Threshold PriceResumption DateResumption Quote TimeResumption Trade Time10/16/2025                    19:50:00PCPremium Catering Hold Ltd OSNASDAQT12",
        "published": "Thu, 16 Oct 2025 04:00:00 GMT"
      },
      {
        "ticker": "NUTR",
        "halt_reason": "",
        "title": "NUTR",
        "description": "Halt DateHalt TimeIssue SymbolIssue NameMarketReason CodePause Threshold PriceResumption DateResumption Quote TimeResumption Trade Time10/08/2025                    19:50:00NUTRNusatrip Incorporated Comm StkNASDAQT12",
        "published": "Wed, 08 Oct 2025 04:00:00 GMT"
      },
      {
        "ticker": "EMPG",
        "halt_reason": "",
        "title": "EMPG",
        "description": "Halt DateHalt TimeIssue SymbolIssue NameMarketReason CodePause Threshold PriceResumption DateResumption Quote TimeResumption Trade Time10/08/2025                    19:50:00EMPGEmpro Group Inc.NASDAQT12",
        "published": "Wed, 08 Oct 2025 04:00:00 GMT"
      },
      {
        "ticker": "PTNM",
        "halt_reason": "",
        "title": "PTNM",
        "description": "Halt DateHalt TimeIssue SymbolIssue NameMarketReason CodePause Threshold PriceResumption DateResumption Quote TimeResumption Trade Time10/03/2025                    19:50:00PTNMPitanium Ltd Ord ANASDAQT12",
        "published": "Fri, 03 Oct 2025 04:00:00 GMT"
      },
      {
        "ticker": "PLTS",
        "halt_reason": "",
        "title": "PLTS",
        "description": "Halt DateHalt TimeIssue SymbolIssue NameMarketReason CodePause Threshold PriceResumption DateResumption Quote TimeResumption Trade Time10/03/2025                    19:50:00PLTSPlatinum Analytics Cymn Ord ANASDAQT12",
        "published": "Fri, 03 Oct 2025 04:00:00 GMT"
      },
      {
        "ticker": "EFTY",
        "halt_reason": "",
        "title": "EFTY",
        "description": "Halt DateHalt TimeIssue SymbolIssue NameMarketReason CodePause Threshold PriceResumption DateResumption Quote TimeResumption Trade Time10/03/2025                    19:50:00EFTYEtoiles Capital Group Cl A OSNASDAQT12",
        "published": "Fri, 03 Oct 2025 04:00:00 GMT"
      },
      {
        "ticker": "UCFI",
        "halt_reason": "",
        "title": "UCFI",
        "description": "Halt DateHalt TimeIssue SymbolIssue NameMarketReason CodePause Threshold PriceResumption DateResumption Quote TimeResumption Trade Time10/01/2025                    11:28:10UCFICN Healthy Food Tech Group CS NASDAQT12",
        "published": "Wed, 01 Oct 2025 04:00:00 GMT"
      },
      {
        "ticker": "UCFIW",
        "halt_reason": "",
        "title": "UCFIW",
        "description": "Halt DateHalt TimeIssue SymbolIssue NameMarketReason CodePause Threshold PriceResumption DateResumption Quote TimeResumption Trade Time10/01/2025                    11:28:10UCFIWCN Healthy Food Tech WarrantNASDAQT12",
        "published": "Wed, 01 Oct 2025 04:00:00 GMT"
      },
      {
        "ticker": "SDM",
        "halt_reason": "",
        "title": "SDM",
        "description": "Halt DateHalt TimeIssue SymbolIssue NameMarketReason CodePause Threshold PriceResumption DateResumption Quote TimeResumption Trade Time09/26/2025                    19:50:00SDMSmart Digital Group Limited OSNASDAQT12",
        "published": "Fri, 26 Sep 2025 04:00:00 GMT"
      },
      {
        "ticker": "QMMM",
        "halt_reason": "",
        "title": "QMMM",
        "description": "Halt DateHalt TimeIssue SymbolIssue NameMarketReason CodePause Threshold PriceResumption DateResumption Quote TimeResumption Trade Time09/26/2025                    19:50:00QMMMQMMM Hldgs Ord Shs ANASDAQT12",
        "published": "Fri, 26 Sep 2025 04:00:00 GMT"
      },
      {
        "ticker": "OST",
        "halt_reason": "",
        "title": "OST",
        "description": "Halt DateHalt TimeIssue SymbolIssue NameMarketReason CodePause Threshold PriceResumption DateResumption Quote TimeResumption Trade Time09/12/2025                    12:24:23OSTOstin Tech Grp Co Ord Cl A OrdNASDAQT12",
        "published": "Fri, 12 Sep 2025 04:00:00 GMT"
      },
      {
        "ticker": "SVA",
        "halt_reason": "",
        "title": "SVA",
        "description": "Halt DateHalt TimeIssue SymbolIssue NameMarketReason CodePause Threshold PriceResumption DateResumption Quote TimeResumption Trade Time02/22/2019                    16:02:01SVASinovac Biotech, Ltd Ord ShrsNASDAQT12",
        "published": "Fri, 22 Feb 2019 05:00:00 GMT"
      }
    ],
    "feed_pubdate": null
  }
}